vscext/__init__.py
vscext-0.2.2.dist-info/LICENSE
vscext-0.2.2.dist-info/METADATA
vscext-0.2.2.dist-info/WHEEL
vscext-0.2.2.dist-info/top_level.txt
vscext-0.2.2.dist-info/RECORD
