Metadata-Version: 2.1
Name: vscext
Version: 0.2.2
Summary: Gives installed VS Code extensions as a linked markdown list
Home-page: https://github.com/inadarei/vscode-extensions-list
Author: Irakli Nadareishvili
License: UNKNOWN
Platform: UNKNOWN
Classifier: Development Status :: 5 - Production/Stable
Classifier: Development Status :: 6 - Mature
Classifier: Intended Audience :: Developers
Classifier: Programming Language :: Python :: 3
Classifier: License :: OSI Approved :: MIT License
Classifier: Operating System :: OS Independent
Requires-Python: >=3.6.*
Requires-Dist: logzero (>=1.5.0)
